OPIPP/__init__.py
OPIPP/cooling.py
OPIPP/feature.py
OPIPP/mosaic.py
OPIPP/pattern.py
OPIPP/scope.py
OPIPP/utils.py
OPIPP-0.1.1.dist-info/LICENSE
OPIPP-0.1.1.dist-info/METADATA
OPIPP-0.1.1.dist-info/WHEEL
OPIPP-0.1.1.dist-info/top_level.txt
OPIPP-0.1.1.dist-info/RECORD
