Metadata-Version: 2.1
Name: OPIPP
Version: 0.1.1
Summary: A Python implementation of Optimization-based PIPP, a method for retinal mosaic simulation.
Author-email: Liuyuan He <liyhe@pku.edu.cn>
License: MIT License
Project-URL: Homepage, https://github.com/heliy/OPIPP
Project-URL: Bug Reports, https://github.com/heliy/OPIPP/issues
Project-URL: Source, https://github.com/heliy/OPIPP/
Classifier: Development Status :: 3 - Alpha
Classifier: License :: OSI Approved :: MIT License
Classifier: Programming Language :: Python :: 3
Classifier: Programming Language :: Python :: 3.8
Classifier: Programming Language :: Python :: 3.9
Classifier: Programming Language :: Python :: 3.10
Classifier: Programming Language :: Python :: 3.11
Classifier: Programming Language :: Python :: 3 :: Only
Requires-Python: >=3.8
License-File: LICENSE
Requires-Dist: numpy >=1.20.0
Requires-Dist: scipy >=1.9.0
Requires-Dist: matplotlib >=3.2.0
Requires-Dist: networkx >=2.0.0
